python_compose/__init__.py
python_compose/compose.py
python_compose/spec.py
python_compose/unit/compose_unit.py
python_compose/unit/conda.py
python_compose/unit/poetry.py
python_compose/unit/pyenv_virtualenv.py
python_compose/unit/venv.py
python_compose-1.2.0.dist-info/METADATA
python_compose-1.2.0.dist-info/WHEEL
python_compose-1.2.0.dist-info/entry_points.txt
python_compose-1.2.0.dist-info/licenses/LICENSE
python_compose-1.2.0.dist-info/RECORD
