Metadata-Version: 2.1
Name: python-compose
Version: 1.2.0
Summary: Python Compose, a tool for spinning up many long-running Python services simultaneously.
Author-email: David Rubinstein <drubinstein91@gmail.com>
License: The MIT License (MIT)
License-File: LICENSE
Classifier: Development Status :: 3 - Alpha
Classifier: Intended Audience :: Developers
Classifier: License :: OSI Approved :: MIT License
Classifier: Operating System :: MacOS :: MacOS X
Classifier: Operating System :: Microsoft :: Windows
Classifier: Operating System :: POSIX :: Linux
Classifier: Programming Language :: Python :: 3.8
Classifier: Programming Language :: Python :: 3.9
Classifier: Programming Language :: Python :: 3.10
Classifier: Programming Language :: Python :: 3.11
Requires-Python: >=3.8
Requires-Dist: pydantic
Requires-Dist: pydantic-yaml
Requires-Dist: ruamel-yaml
Requires-Dist: types-pyyaml
Requires-Dist: typing-extensions
Provides-Extra: dev
Requires-Dist: black; extra == 'dev'
Requires-Dist: bump2version; extra == 'dev'
Requires-Dist: hatch; extra == 'dev'
Requires-Dist: isort; extra == 'dev'
Requires-Dist: mypy; extra == 'dev'
Requires-Dist: pre-commit; extra == 'dev'
Requires-Dist: python-compose[test]; extra == 'dev'
Requires-Dist: ruff; extra == 'dev'
Provides-Extra: poetry
Requires-Dist: poetry; extra == 'poetry'
Provides-Extra: test
Requires-Dist: pytest; extra == 'test'
Requires-Dist: python-compose[poetry]; extra == 'test'
